mfj/__init__.py
mfj-0.1.0.dist-info/METADATA
mfj-0.1.0.dist-info/WHEEL
mfj-0.1.0.dist-info/RECORD
