Metadata-Version: 2.3
Name: mfj
Version: 0.1.0
Summary: migrations for json files
Author: dvodnenko
Author-email: thekovalskii@gmail.com
Requires-Python: >=3.9
Classifier: Programming Language :: Python :: 3
Classifier: Programming Language :: Python :: 3.9
Classifier: Programming Language :: Python :: 3.10
Classifier: Programming Language :: Python :: 3.11
Classifier: Programming Language :: Python :: 3.12
Classifier: Programming Language :: Python :: 3.13
